[{
        "id": 20,
        "nom": "Anouilh",
        "prenom": "Jean",
        "date_de_naissance": "23 juin 1910",
        "lieu_de_naissance": "Bordeaux",
        "date_de_deces": "3 octobre 1987",
        "lieu_de_deces": "Lausanne",
        "photo": "anouilh.jpeg",
        "oeuvres_majeures": "Le voyageur sans bagage - Le Bal des voleurs - Antigone",
        "citation1": "\"Ce qui est beau, c'est ce qu'on aime.\"",
        "oeuvreCitation1": "Colombe",
        "citation2": "\"Pourquoi contredire une femme ? Il est tellement plus simple d'attendre qu'elle change d'avis.\"",
        "oeuvreCitation2": "",
        "citation3": "\"La beauté est une des rares choses qui ne font pas douter de Dieu.\"",
        "oeuvreCitation3": "Becket ou l'honneur de Dieu"
    },
    {
        "id": 50,
        "nom": "Apollinaire",
        "prenom": "Guillaume",
        "date_de_naissance": "25 août 1880",
        "lieu_de_naissance": "Rome",
        "date_de_deces": "9 novembre 1918",
        "lieu_de_deces": "Paris",
        "photo": "apollinaire.jpg",
        "oeuvres_majeures": "Alcools - Calligrammes - Poèmes à Lou - Le Poète assassiné",
        "citation1": "\"Il est grand temps de rallumer les étoiles.\"",
        "oeuvreCitation1": "Les mamelles de Tirésias",
        "citation2": "\"Vienne la nuit sonne l'heure Les jours s'en vont je demeure\"",
        "oeuvreCitation2": "Le Pont Mirabeau",
        "citation3": "\"Les feuilles Qu'on foule Un train Qui roule La vie S'écoule\"",
        "oeuvreCitation3": ""
    },
    {
        "id": 70,
        "nom": "Aragon",
        "prenom": "Louis",
        "date_de_naissance": "3 octobre 1897",
        "lieu_de_naissance": "Paris",
        "date_de_deces": "24 décembre 1982",
        "lieu_de_deces": "Paris",
        "photo": "aragon.jpg",
        "oeuvres_majeures": "Les Aventures de Télémaque - Les Yeux d'Elsa - Le Roman inachevé",
        "citation1": "\"L'avenir de l'homme, c'est la femme. Elle est la couleur de son âme.\"",
        "oeuvreCitation1": "Le fou d'Elsa",
        "citation2": "\"Le temps d'apprendre à vivre, il est déjà trop tard.\"",
        "oeuvreCitation2": "",
        "citation3": "\"Il n'y a pas de lumière sans ombre.\"",
        "oeuvreCitation3": "J'abats mon jeu"
    },
    {
        "id": 100,
        "nom": "Balzac",
        "prenom": "Honoré de",
        "date_de_naissance": "20 mai 1799",
        "lieu_de_naissance": "Tours",
        "date_de_deces": "18 août 1850",
        "lieu_de_deces": "Paris",
        "photo": "balzac.jpg",
        "oeuvres_majeures": "La Comédie humaine - Les Chouans - La Peau de chagrin - Eugénie Grandet - Le Père Goriot - Le Colonel Chabert",
        "citation1": "\"Les gens généreux font de mauvais commerçants.\"",
        "oeuvreCitation1": "Illusions perdues",
        "citation2": "\"Un homme est bien fort lorsqu'il s'avoue sa faiblesse.\"",
        "oeuvreCitation2": "La Peau de chagrin",
        "citation3": "\"On peut pardonner, mais oublier, c'est impossible.\"",
        "oeuvreCitation3": "Petites Misères de la vie conjugale"
    },
    {
        "id": 110,
        "nom": "Baudelaire",
        "prenom": "Charles",
        "date_de_naissance": "9 avril 1821",
        "lieu_de_naissance": "Paris",
        "date_de_deces": "31 août 1867",
        "lieu_de_deces": "Paris",
        "photo": "baudelaire.jpg",
        "oeuvres_majeures": "Les Fleurs du Mal - Le Spleen de Paris",
        "citation1": "\"Mon enfant, songe à la douceur d'aller là-bas vivre ensemble ; aimer à loisir, aimer et mourir, au pays qui te ressemble !\"",
        "oeuvreCitation1": "L'invitation au voyage (1857)",
        "citation2": "\"Il me semble que je serais toujours bien là où je ne suis pas.\"",
        "oeuvreCitation2": "Le spleen de Paris, N'importe où hors du monde (posthume, 1869)",
        "citation3": "\"C'est par le malentendu universel que tout le monde s'accorde.\"",
        "oeuvreCitation3": "Mon cœur mis à nu, journal intime (1864)"
    },
    {
        "id": 130,
        "nom": "Beaumarchais",
        "prenom": "Pierre-Augustin Caron de",
        "date_de_naissance": "24 janvier 1732",
        "lieu_de_naissance": "Paris",
        "date_de_deces": "18 mai 1799",
        "lieu_de_deces": "Paris",
        "photo": "beaumarchais.jpg",
        "oeuvres_majeures": "Le Barbier de Séville - Le Mariage de Figaro - La Mère coupable",
        "citation1": "\"Sans la liberté de blâmer, il n'est point d'éloge flatteur.\"",
        "oeuvreCitation1": "Le Mariage de Figaro",
        "citation2": "\"Je me presse de rire de tout, de peur d'être obligé d'en pleurer.\"",
        "oeuvreCitation2": "Le Barbier de Séville",
        "citation3": "\"Il est doux d'être aimé pour soi-même.\"",
        "oeuvreCitation3": ""
    },
    {
        "id": 150,
        "nom": "Beckett",
        "prenom": "Samuel",
        "date_de_naissance": "13 avril 1906",
        "lieu_de_naissance": "Foxrock (Dublin)",
        "date_de_deces": "22 décembre 1989",
        "lieu_de_deces": "Paris",
        "photo": "beckett.jpg",
        "oeuvres_majeures": "En attendant Godot - Fin de partie - Oh les beaux jours",
        "citation1": "\"Nous naissons tous fous. Quelques-uns le demeurent.\"",
        "oeuvreCitation1": "En attendant Godot",
        "citation2": "\"Se donner du mal pour les petites choses, c’est parvenir aux grandes, avec le temps.\"",
        "oeuvreCitation2": "Molloy",
        "citation3": "\"On dit tout. Tout ce qu'on peut. Et pas un mot de vrai nulle part.\"",
        "oeuvreCitation3": "Oh les beaux jours"
    },
    {
        "id": 200,
        "nom": "Camus",
        "prenom": "Albert",
        "date_de_naissance": "7 novembre 1913",
        "lieu_de_naissance": "Mondovi (aujourd'hui Dréan)",
        "date_de_deces": "4 janvier 1960",
        "lieu_de_deces": "Villeblevin",
        "photo": "camus.jpg",
        "oeuvres_majeures": "L'Homme révolté - La Mort heureuse - La Chute - Le Mythe de Sisyphe - L'Etranger",
        "citation1": "\"Un exemple n'est pas forcément un exemple à suivre.\"",
        "oeuvreCitation1": "Le Mythe de Sisyphe",
        "citation2": "\"Les doutes, c'est ce que nous avons de plus intime.\"",
        "oeuvreCitation2": "Carnets",
        "citation3": "\"La bêtise insiste toujours.\"",
        "oeuvreCitation3": "La Peste"
    },
    {
        "id": 240,
        "nom": "Céline",
        "prenom": "Louis-Ferdinand",
        "date_de_naissance": "27 mai 1894",
        "lieu_de_naissance": "Courbevoie",
        "date_de_deces": "1er juillet 1961",
        "lieu_de_deces": "Meudon",
        "photo": "celine.jpg",
        "oeuvres_majeures": "Voyage au bout de la nuit - Mort à crédit - D'un château l'autre",
        "citation1": "\"Avec les mots on ne se méfie jamais suffisamment.\"",
        "oeuvreCitation1": "Voyage au bout de la nuit",
        "citation2": "\"Il faut choisir, mourir ou mentir.\"",
        "oeuvreCitation2": "",
        "citation3": "\"La conscience n'est dans le chaos du monde qu'une petite lumière, précieuse mais fragile.”\"",
        "oeuvreCitation3": ""
    },
    {
        "id": 250,
        "nom": "Chateaubriand",
        "prenom": "François-René de",
        "date_de_naissance": "4 septembre 1768",
        "lieu_de_naissance": "Saint-Malo",
        "date_de_deces": "4 juillet 1848",
        "lieu_de_deces": "Paris",
        "photo": "chateaubriand.jpg",
        "oeuvres_majeures": "Atala - René - Génie du christianisme - Mémoires d'outre-tombe - Vie de Rancé",
        "citation1": "\"Le péril s'évanouit quand on ose le regarder.\"",
        "oeuvreCitation1": "Mémoires d'outre-tombe",
        "citation2": "\"Les forêts précèdent les peuples, les déserts les suivent.\"",
        "oeuvreCitation2": "",
        "citation3": "\"Tant que le coeur conserve des souvenirs, l'esprit garde des illusions.”\"",
        "oeuvreCitation3": ""
    },
    {
        "id": 260,
        "nom": "Corneille",
        "prenom": "Pierre",
        "date_de_naissance": "6 juin 1606",
        "lieu_de_naissance": "Rouen",
        "date_de_deces": "1er octobre 1684",
        "lieu_de_deces": "Paris",
        "photo": "corneille.jpg",
        "oeuvres_majeures": "Médée - L'Illusion comique - Le Cid",
        "citation1": "\"Aux âmes bien nées, La valeur n’attend point le nombre des années.\"",
        "oeuvreCitation1": "Le Cid",
        "citation2": "\"A qui sait bien aimer, il n’est rien d’impossible.\"",
        "oeuvreCitation2": "Médée",
        "citation3": "\"O rage ! O désespoir ! O vieillesse ennemie ! N’ai-je donc tant tant vécu que pour cette infamie ?”\"",
        "oeuvreCitation3": "Le Cid"
    },
    {
        "id": 300,
        "nom": "Daudet",
        "prenom": "Alphonse",
        "date_de_naissance": "13 mai 1840",
        "lieu_de_naissance": "Nîmes",
        "date_de_deces": "16 décembre 1897",
        "lieu_de_deces": "Paris",
        "photo": "daudet.jpg",
        "oeuvres_majeures": "Tartarin de Tarascon - Lettres de mon moulin - Le petit Chose - La chèvre de monsieur Seguin - L'Arlésienne",
        "citation1": "\"La gourmandise commence quand on n'a plus faim.\"",
        "oeuvreCitation1": "Les lettres de mon moulin (1870)",
        "citation2": "\"La haine, c'est la colère des faibles !\"",
        "oeuvreCitation2": "Les lettres de mon moulin (1870)",
        "citation3": "\"Il y a parfois du courage à fuir.\"",
        "oeuvreCitation3": "Le frère aîné (1867)"
    },
    {
        "id": 310,
        "nom": "De Beauvoir",
        "prenom": "Simone",
        "date_de_naissance": "9 janvier 1908",
        "lieu_de_naissance": "Paris",
        "date_de_deces": "14 avril 1986",
        "lieu_de_deces": "Paris",
        "photo": "de_beauvoir.png",
        "oeuvres_majeures": "Le Deuxième Sexe - Les Mandarins - L'Invitée - Les Belles Images",
        "citation1": "\"Une femme libre est exactement le contraire d'une femme légère.\"",
        "oeuvreCitation1": "",
        "citation2": "\"Si l'on vit assez longtemps, on voit que toute victoire se change un jour en défaite.\"",
        "oeuvreCitation2": "",
        "citation3": "\"La beauté se raconte encore moins que le bonheur.\"",
        "oeuvreCitation3": "La Force de l'âge (1960)"
    },
    {
        "id": 330,
        "nom": "De Musset",
        "prenom": "Alfred",
        "date_de_naissance": "11 décembre 1810",
        "lieu_de_naissance": "Paris",
        "date_de_deces": "2 mai 1857",
        "lieu_de_deces": "Paris",
        "photo": "de_musset.jpg",
        "oeuvres_majeures": "Les Caprices de Marianne - On ne badine pas avec l'amour - Lorenzaccio - La confession d'un enfant du siècle",
        "citation1": "\"Nul ne se connaît tant qu'il n'a pas souffert.\"",
        "oeuvreCitation1": "La nuit d'octobre (1835)",
        "citation2": "\"Une larme est ce qu'il y a de plus vrai, de plus impérissable au monde.\"",
        "oeuvreCitation2": "Le poète déchu, VII (1839)",
        "citation3": "\"On ne badine pas avec l'amour.\"",
        "oeuvreCitation3": "On ne badine pas avec l'amour (1834)"
    },
    {
        "id": 350,
        "nom": "Diderot",
        "prenom": "Denis",
        "date_de_naissance": "5 octobre 1713",
        "lieu_de_naissance": "Langres",
        "date_de_deces": "31 juillet 1784",
        "lieu_de_deces": "Paris",
        "photo": "diderot.png",
        "oeuvres_majeures": "L'Encyclopédie",
        "citation1": "\"Ôtez à l'homme le bon sens, et vous le réduirez à la qualité d'automate ou d'enfant.\"",
        "oeuvreCitation1": "L'encyclopédie (1747-1765)",
        "citation2": "\"L'éloquence n'est que l'art d'embellir la logique.\"",
        "oeuvreCitation2": "Pensées détachées sur la peinture (1772-1784)",
        "citation3": "\"La politesse est aux actions ce que la grâce est à la beauté.\"",
        "oeuvreCitation3": "Les maximes, réflexions et pensées (1784)"
    },
    {
        "id": 370,
        "nom": "Dostoïevski",
        "prenom": "Fiodor",
        "date_de_naissance": "30 octobre 1821",
        "lieu_de_naissance": "Moscou",
        "date_de_deces": "28 janvier 1881",
        "lieu_de_deces": "Saint-Pétersbourg",
        "photo": "dostoievski.jpg",
        "oeuvres_majeures": "Les Frères Karamazov - Crime et Châtiment - L'idiot - Le Joueur",
        "citation1": "\"La beauté sauvera le monde.\"",
        "oeuvreCitation1": "L'idiot",
        "citation2": "\"Si Dieu n'existe pas, tout est permis.\"",
        "oeuvreCitation2": "Les Frères Karamazov",
        "citation3": "\"L'homme est malheureux parce qu'il ne sait pas qu'il est heureux.\"",
        "oeuvreCitation3": "Les Démons"
    },
    {
        "id": 389,
        "nom": "Dumas (fils)",
        "prenom": "Alexandre",
        "date_de_naissance": "27 juillet 1824",
        "lieu_de_naissance": "Paris",
        "date_de_deces": "27 novembre 1895",
        "lieu_de_deces": "Marly-le-Roi",
        "photo": "dumas_fils.jpg",
        "oeuvres_majeures": "La Dame aux camélias - Le Fils naturel - Un père prodigue",
        "citation1": "\"Les larmes deviennent une chose si rare qu'on ne peut les donner à la première venue.\"",
        "oeuvreCitation1": "La Dame aux camélias",
        "citation2": "\"Le devoir, c'est ce qu'on exige des autres.\"",
        "oeuvreCitation2": "Denise",
        "citation3": "\"Quand on tombe, on ne tombe jamais bien.\"",
        "oeuvreCitation3": "Le Demi-Monde"
    },
    {
        "id": 390,
        "nom": "Dumas (père)",
        "prenom": "Alexandre",
        "date_de_naissance": "24 juillet 1802",
        "lieu_de_naissance": "Villers-Cotterêts",
        "date_de_deces": "5 décembre 1870",
        "lieu_de_deces": "Neuville-lès-Dieppe",
        "photo": "dumas_pere.jpg",
        "oeuvres_majeures": "Le Comte de Monte-Cristo - Les Trois Mousquetaires - La Reine Margot - Vingt ans après - La Dame de Monsoreau",
        "citation1": "\"C'est quelques fois pénible de faire son devoir, mais ça ne l'est jamais autant que de ne pas l'avoir fait.\"",
        "oeuvreCitation1": "",
        "citation2": "\"En amour, qui doute accuse.\"",
        "oeuvreCitation2": "",
        "citation3": "\"J'aime mieux les méchants que les imbéciles, parcequ'ils se reposent.\"",
        "oeuvreCitation3": ""
    },
    {
        "id": 400,
        "nom": "Eluard",
        "prenom": "Paul",
        "date_de_naissance": "14 décembre 1895",
        "lieu_de_naissance": "Saint-Denis",
        "date_de_deces": "18 novembre 1852",
        "lieu_de_deces": "Charenton-le-Pont",
        "photo": "eluard.jpg",
        "oeuvres_majeures": "Capitale de la douleur - Liberté - Poésie et Vérité",
        "citation1": "\"Il nous faut peu de mots pour exprimer l’essentiel.\"",
        "oeuvreCitation1": "Avenir de la poésie",
        "citation2": "\"Il ne faut pas de tout pour faire un monde. Il faut du bonheur, et rien d’autre.\"",
        "oeuvreCitation2": "Le Château des pauvres",
        "citation3": "\"Un coeur n'est juste que s'il bat au rythme des autres coeurs.\"",
        "oeuvreCitation3": "Poèmes retrouvés"
    },
    {
        "id": 500,
        "nom": "Flaubert",
        "prenom": "Gustave",
        "date_de_naissance": "12 décembre 1821",
        "lieu_de_naissance": "Rouen",
        "date_de_deces": "8 mai 1880",
        "lieu_de_deces": "Croisset",
        "photo": "flaubert.jpg",
        "oeuvres_majeures": "Madame Bovary - Salammbô - L'Education sentimentale - Trois contes",
        "citation1": "\"On vit fort bien sans se connaître soi-même, à plus forte raison sans être connu des autres.\"",
        "oeuvreCitation1": "",
        "citation2": "\"Le seul moyen de guérir, c'est de se considérer comme guéri.\"",
        "oeuvreCitation2": "",
        "citation3": "\"L'avenir nous tourmente, le passé nous retient, c'est pour ça que le présent nous échappe.\"",
        "oeuvreCitation3": ""
    },
    {
        "id": 600,
        "nom": "Gide",
        "prenom": "André",
        "date_de_naissance": "22 novembre 1869",
        "lieu_de_naissance": "Paris",
        "date_de_deces": "19 février 1951",
        "lieu_de_deces": "Paris",
        "photo": "gide.jpg",
        "oeuvres_majeures": "L'Immoraliste - La Porte étroite - La Symphonie pastorale - Les Faux-monnayeurs",
        "citation1": "\"Toutes choses sont dites déjà ; mais personne n'écoute, il faut toujours recommencer.\"",
        "oeuvreCitation1": "Traité du Narcisse",
        "citation2": "\"Pour moi, être aimé n'est rien, c'est être préféré que je désire.\"",
        "oeuvreCitation2": "Lettre à Paul Valéry",
        "citation3": "\"Un bon maître a ce souci constant : enseigner à se passer de lui.\"",
        "oeuvreCitation3": "Journal"
    },
    {
        "id": 650,
        "nom": "Gogol",
        "prenom": "Nicolas",
        "date_de_naissance": "20 mars 1809",
        "lieu_de_naissance": "Sorotchintsy",
        "date_de_deces": "21 février 1852",
        "lieu_de_deces": "Moscou",
        "photo": "gogol.jpg",
        "oeuvres_majeures": "Nouvelles de Pétersbourg (Le nez, Le Journal d'un Fou...) - Les Ames mortes - Tarass Boulba - Le Révizor",
        "citation1": "\"Ah, les Russes ! Ils n’aiment vraiment pas mourir de mort naturelle.\"",
        "oeuvreCitation1": "Les Ames mortes",
        "citation2": "\"Aujourd’hui, toute nullité parvenue se prend pour un aristocrate.\"",
        "oeuvreCitation2": "Le Révizor",
        "citation3": "\"L'homme est sage, intelligent et raisonnable en tout ce qui concerne les autres, mais pas en ce qui le touche lui-même.\"",
        "oeuvreCitation3": ""
    },
    {
        "id": 700,
        "nom": "Hemingway",
        "prenom": "Ernest",
        "date_de_naissance": "21 juillet 1899",
        "lieu_de_naissance": "Oak Park",
        "date_de_deces": "2 juillet 1961",
        "lieu_de_deces": "Ketchum",
        "photo": "hemingway.jpg",
        "oeuvres_majeures": "Le soleil se lève aussi - L'Adieu aux armes - Les Neiges du Kilimandjaro - Pour qui sonne le glas - Le Viel Homme et la Mer - Paris est une fête (posthume, 1964)",
        "citation1": "\"Dans tous les arts, le plaisir croît avec la connaissance que l'on a d'eux.\"",
        "oeuvreCitation1": "Mort dans l'après-midi (1938)",
        "citation2": "\"Un homme intelligent est parfois obligé d'être saoul pour passer du temps avec les imbéciles.\"",
        "oeuvreCitation2": "",
        "citation3": "\"Il n'y a rien de noble à être supérieur à vos semblables. La vraie noblesse est d'être supérieur à celui que vous avez été auparavant.\"",
        "oeuvreCitation3": ""
    },
    {
        "id": 790,
        "nom": "Hugo",
        "prenom": "Victor",
        "date_de_naissance": "26 février 1802",
        "lieu_de_naissance": "Besançon",
        "date_de_deces": "22 mai 1885",
        "lieu_de_deces": "Paris",
        "photo": "hugo.jpg",
        "oeuvres_majeures": "Notre-Dame de Paris - Les Misérables - Les Travailleurs de la mer - Les Contemplations - Hernani - Ruy Blas",
        "citation1": "\"Mais si l'on ne peut pardonner, cela ne vaut pas la peine de vaincre.\"",
        "oeuvreCitation1": "Quatre-vingt-treize",
        "citation2": "\"On passe une moitié de sa vie à attendre ceux qu'on aimera et l'autre moitié à quitter ceux qu'on aime.\"",
        "oeuvreCitation2": "Tas de pierres",
        "citation3": "\"L'avenir, fantôme aux mains vides, qui promet tout et qui n'a rien !\"",
        "oeuvreCitation3": "Les Voix intérieures"
    },
    {
        "id": 1000,
        "nom": "Kessel",
        "prenom": "Joseph",
        "date_de_naissance": "31 janvier 1898",
        "lieu_de_naissance": "Villa Clara",
        "date_de_deces": "23 juillet 1979",
        "lieu_de_deces": "Avernes",
        "photo": "kessel.jpg",
        "oeuvres_majeures": "Belle de jour - Le Lion - Les Mains du miracle",
        "citation1": "\"Personne au monde n'était aussi riche qu'eux, justement parce qu'ils ne possédaient rien et ne désiraient pas davantage.\"",
        "oeuvreCitation1": "Le Lion",
        "citation2": "\"Si la chance est avec toi, pourquoi courir ? Et si la chance n’est pas avec toi, pourquoi courir ?\"",
        "oeuvreCitation2": "Les cavaliers",
        "citation3": "\"Il n'y a pas que l'amour que la raison ne contrôle point.\"",
        "oeuvreCitation3": "Les nuits de Sibérie"
    },
    {
        "id": 1100,
        "nom": "La Fontaine",
        "prenom": "Jean de",
        "date_de_naissance": "8 juillet 1621",
        "lieu_de_naissance": "Château-Thierry",
        "date_de_deces": "13 avril 1695",
        "lieu_de_deces": "Paris",
        "photo": "la_fontaine.jpg",
        "oeuvres_majeures": "Les Fables",
        "citation1": "\"Rien ne sert de courir, il faut partir à point.\"",
        "oeuvreCitation1": "Le lièvre et la tortue",
        "citation2": "\"La raison du plus fort est toujours la meilleure.\"",
        "oeuvreCitation2": "Le loup et l'agneau",
        "citation3": "\"Tel est pris qui croyait prendre.\"",
        "oeuvreCitation3": "Le rat et l'huître"
    },
    {
        "id": 1150,
        "nom": "Lamartine",
        "prenom": "Alphonse de",
        "date_de_naissance": "21 octobre 1790",
        "lieu_de_naissance": "Mâcon",
        "date_de_deces": "28 février 1869",
        "lieu_de_deces": "Paris",
        "photo": "lamartine.png",
        "oeuvres_majeures": "Méditations poétiques - Harmonies poétiques et religieuses - Jocelyn - Graziella",
        "citation1": "\"Un seul être vous manque et tout est dépeuplé.\"",
        "oeuvreCitation1": "L'isolement (1815 - 1820)",
        "citation2": "\"Le flambeau de l'étude éclaire la raison.\"",
        "oeuvreCitation2": "Méditations poétiques, La retraite (1820)",
        "citation3": "\"La coupe de mes jours s'est brisée encore pleine.\"",
        "oeuvreCitation3": "Le poète mourant (1815 - 1820)"
    },
    {
        "id": 1200,
        "nom": "Malraux",
        "prenom": "André",
        "date_de_naissance": "3 novembre 1901",
        "lieu_de_naissance": "Paris",
        "date_de_deces": "23 novembre 1976",
        "lieu_de_deces": "Créteil",
        "photo": "malraux.jpeg",
        "oeuvres_majeures": "Les Conquérants - La Condition humaine - La Métamorphose des dieux",
        "citation1": "\"Une vie ne vaut rien, mais rien ne vaut une vie.\"",
        "oeuvreCitation1": "Les Conquérants",
        "citation2": "\"On ne voit vieillir que les autres.\"",
        "oeuvreCitation2": "Les chênes qu'on abat",
        "citation3": "\"La pire souffrance est dans la solitude qui l'accompagne.\"",
        "oeuvreCitation3": "La condition humaine"
    },
    {
        "id": 1210,
        "nom": "Maupassant",
        "prenom": "Guy de",
        "date_de_naissance": "5 août 1850",
        "lieu_de_naissance": "Tourville-sur-Arques",
        "date_de_deces": "6 juillet 1893",
        "lieu_de_deces": "Paris",
        "photo": "maupassant.jpg",
        "oeuvres_majeures": "Bel-Ami - Boule de suif - Le Horla",
        "citation1": "\"L'air du matin est plein de frissons mystérieux que ne connaissent point les attardés du lit.\"",
        "oeuvreCitation1": "Sur l'eau, le 22 mai 1881",
        "citation2": "\"La vie n'est pas monotone quand on sait s'occuper.\"",
        "oeuvreCitation2": "Le rosier de Mme Husson (1888)",
        "citation3": "\"Une vie... quelques jours, et puis plus rien.\"",
        "oeuvreCitation3": "Bel-Ami (1885)"
    },
    {
        "id": 1224,
        "nom": "Mirabeau",
        "prenom": "Honoré-Gabriel Riqueti de",
        "date_de_naissance": "9 mars 1749",
        "lieu_de_naissance": "Bignon-Mirabeau",
        "date_de_deces": "2 avril 1791",
        "lieu_de_deces": "Paris",
        "photo": "mirabeau.jpg",
        "oeuvres_majeures": "Sur la liberté de la presse - Au club des Jacobins, discours contre la traite des noirs",
        "citation1": "\"Allez dire à ceux qui vous envoient que nous sommes ici par la volonté du peuple, et qu'on ne nous en arrachera que par la puissance des baïonnettes.\"",
        "oeuvreCitation1": "Lors de la séance royale du 23 juin 1789",
        "citation2": "\"La beauté sans grâce est un printemps sans verdure.\"",
        "oeuvreCitation2": "Les lettres à Sophie Ruffei (1777-1780)",
        "citation3": "\"Trop gouverner est le plus grand danger des gouvernements.\"",
        "oeuvreCitation3": "Discours Assemblée nationale, le 25 novembre 1790"
    },
    {
        "id": 1250,
        "nom": "Molière",
        "prenom": "(Jean-Baptiste Poquelin)",
        "date_de_naissance": "15 janvier 1622 (baptisé)",
        "lieu_de_naissance": "Paris",
        "date_de_deces": "17 février 1673",
        "lieu_de_deces": "Paris",
        "photo": "moliere.jpg",
        "oeuvres_majeures": "Les Précieuses ridicules - L'Ecole des Femmes - Dom Juan ou le festin de Pierre - Le Misanthrope - Amphhytrion - L'Avare - Le Tartuffe - Le Dépit amoureux - Le Médecin malgré lui - Les Fourberies de Scapin - Les Femmes savantes - Le Malade imaginaire - Le Bourgeois gentilhomme",
        "citation1": "\"L'hypocrisie est un vice  à la mode, et tous les vices à la mode passent pour vertus.\"",
        "oeuvreCitation1": "Dom Juan (1665)",
        "citation2": "\"Un sot savant est sot plus qu'un sot ignorant.\"",
        "oeuvreCitation2": "Les Femmes savantes (1672)",
        "citation3": "\"On ne meurt qu'une fois, et c'est pour si longtemps !\"",
        "oeuvreCitation3": "Le Dépit amoureux (1656)"
    },
    {
        "id": 1260,
        "nom": "Montesquieu",
        "prenom": "Charles Louis de Secondat, baron de la Brède et de",
        "date_de_naissance": "18 janvier 1689",
        "lieu_de_naissance": "La Brède",
        "date_de_deces": "10 février 1755",
        "lieu_de_deces": "Paris",
        "photo": "montesquieu.jpg",
        "oeuvres_majeures": "Lettres persanes - Les considérations - De l'esprit des lois",
        "citation1": "\"Une chose n’est pas juste parce qu’elle est loi ; mais elle doit être loi parce qu’elle est juste.\"",
        "oeuvreCitation1": "Cahiers",
        "citation2": "\"L’homme pieux et l’athée parlent toujours de religion : l’un parle de ce qu’il aime, et l’autre ce qu’il craint.\"",
        "oeuvreCitation2": "De l'esprit des lois",
        "citation3": "\"Un homme n’est pas malheureux parce qu’il a de l’ambition, mais parce qu’il en est dévoré.\"",
        "oeuvreCitation3": "Sur l'homme"
    },
    {
        "id": 1500,
        "nom": "Pagnol",
        "prenom": "Marcel",
        "date_de_naissance": "28 février 1895",
        "lieu_de_naissance": "Aubagne",
        "date_de_deces": "18 avril 1874",
        "lieu_de_deces": "Paris",
        "photo": "pagnol.jpg",
        "oeuvres_majeures": "La Gloire de mon père - Le Château de ma mère - Manon des sources",
        "citation1": "\"Si vous voulez aller sur la mer, sans aucun risque de chavirer, alors, n'achetez pas un bateau : achetez une île !\"",
        "oeuvreCitation1": "Fanny",
        "citation2": "\"Quand on apporte une mauvaise nouvelle, personne ne pense à vous offrir à boire.\"",
        "oeuvreCitation2": "César",
        "citation3": "\"'Tout le monde savait que c'était impossible. Il est venu un imbécile qui ne le savait pas et qui l'a fait.\"",
        "oeuvreCitation3": ""
    },
    {
        "id": 1550,
        "nom": "Perrault",
        "prenom": "Charles",
        "date_de_naissance": "12 janvier 1628",
        "lieu_de_naissance": "Paris",
        "date_de_deces": "16 mai 1703",
        "lieu_de_deces": "Paris",
        "photo": "perrault.jpg",
        "oeuvres_majeures": "Peau d'âne - La Belle au bois dormant - Le Petit Chaperon rouge - Barbe-Bleue - Le Chat botté - Cendrillon - Riquet à la houppe - Le Petit Poucet - Les Contes de ma mère l'Oye",
        "citation1": "\"Anne, ma soeur Anne, ne vois-tu rien venir ?\"",
        "oeuvreCitation1": "Barbe-Bleue",
        "citation2": "\"On n'est heureux qu'autant qu'on a souffert.\"",
        "oeuvreCitation2": "Griselidis (La Marquise de Salusses)",
        "citation3": "\"'Trop de bonté dans les parents cause la perte des enfants.\"",
        "oeuvreCitation3": ""
    },
    {
        "id": 1560,
        "nom": "Pouchkine",
        "prenom": "Alexandre",
        "date_de_naissance": "26 mai 1799",
        "lieu_de_naissance": "Moscou",
        "date_de_deces": "29 janvier 1837",
        "lieu_de_deces": "Saint-Pétersbourg",
        "photo": "pouchkine.jpg",
        "oeuvres_majeures": "Eugène Onéguine - Boris Godounov - Poésies - L'or et l'épée",
        "citation1": "\"L'habitude est l'âme des Etats.\"",
        "oeuvreCitation1": "Boris Godounov",
        "citation2": "\"Ce que nous recherchons, c'est le fruit défendu. Sans lui, le Paradis n'est pas pour nous le Paradis.\"",
        "oeuvreCitation2": "Eugène Onéguine",
        "citation3": "\"'J'achèterai tout', a dit l'or ; 'Je prendrai tout', a dit l'épée.\"",
        "oeuvreCitation3": "L'or et l'épée."
    },
    {
        "id": 1580,
        "nom": "Prévert",
        "prenom": "Jacques",
        "date_de_naissance": "4 février 1900",
        "lieu_de_naissance": "Neuilly-sur-Seine",
        "date_de_deces": "11 avril 1977",
        "lieu_de_deces": "Omonville-la-Petite",
        "photo": "prevert.jpg",
        "oeuvres_majeures": "Paroles",
        "citation1": "\"Il faudrait essayer d'être heureux, ne serait-ce que pour donner l'exemple.\"",
        "oeuvreCitation1": "",
        "citation2": "\"Si quelqu'un vous dit : 'Je me tue à vous le répéter', laissez-le mourir.\"",
        "oeuvreCitation2": "",
        "citation3": "\"'Il dit non avec la tête, mais il dit oui avec le coeur, il dit oui à ce qu'il aime, il dit non au professeur.\"",
        "oeuvreCitation3": ""
    },
    {
        "id": 1590,
        "nom": "Proust",
        "prenom": "Marcel",
        "date_de_naissance": "10 juillet 1871",
        "lieu_de_naissance": "Paris",
        "date_de_deces": "18 novembre 1922",
        "lieu_de_deces": "Paris",
        "photo": "proust.jpg",
        "oeuvres_majeures": "A la recherche du temps perdu - Du côté de chez Swann - A l'ombre des jeunes filles en fleurs - Le temps retrouvé",
        "citation1": "\"Les paradoxes d’aujourd’hui sont les préjugés de demain.\"",
        "oeuvreCitation1": "Les Plaisirs et les jours",
        "citation2": "\"On ne guérit d’une souffrance qu’à condition de l’éprouver pleinement.\"",
        "oeuvreCitation2": "Albertine disparue",
        "citation3": "\"'Ce qui pour nous fait le bonheur ou le malheur de notre vie, constitue pour tout autre un fait presque imperceptible.\"",
        "oeuvreCitation3": "Jean Santeuil"
    },
    {
        "id": 1700,
        "nom": "Rabelais",
        "prenom": "François",
        "date_de_naissance": "1483 ou 1494",
        "lieu_de_naissance": "La Devinière à Seuilly",
        "date_de_deces": "9 avril 1553",
        "lieu_de_deces": "Paris",
        "photo": "rabelais.jpg",
        "oeuvres_majeures": "Pantagruel - Gargantua - Le Tiers Livre - Le Quart Livre - Le Cinquième Livre",
        "citation1": "\"Ce qu'à autrui tu auras fait, soit certain qu'autrui te le fera.\"",
        "oeuvreCitation1": "Le Tiers livre, IX (1546)",
        "citation2": "\"Science sans conscience n'est que ruine de l'âme\"",
        "oeuvreCitation2": "Pantagruel (1532)",
        "citation3": "\"Le rire est le propre de l'homme.\"",
        "oeuvreCitation3": "Gargantua, Aux lecteurs (1534)"
    },
    {
        "id": 1710,
        "nom": "Racine",
        "prenom": "Jean",
        "date_de_naissance": "22 décembre 1639",
        "lieu_de_naissance": "La Ferté-Milon",
        "date_de_deces": "21 avril 1699",
        "lieu_de_deces": "Paris",
        "photo": "racine.jpg",
        "oeuvres_majeures": "Andromaque - Britannicus - Bérénice - Iphigénie - Phèdre",
        "citation1": "\"Quelques crimes toujours précèdent les grands crimes.\"",
        "oeuvreCitation1": "Phèdre, IV, 2, le 1er janvier 1677",
        "citation2": "\"Hâtons-nous aujourd'hui de jouir de la vie ; qui sait si nous serons demain ?\"",
        "oeuvreCitation2": "Athalie, II, 9, le 5 janvier 1691",
        "citation3": "\"Puisse le ciel verser sur toutes vos années, mille prospérités l'une à l'autre enchaînées.\"",
        "oeuvreCitation3": "Bérénice, V, 7 (1670)"
    },
    {
        "id": 1750,
        "nom": "Rimbaud",
        "prenom": "Arthur",
        "date_de_naissance": "20 octobre 1854",
        "lieu_de_naissance": "Charleville",
        "date_de_deces": "10 novembre 1891",
        "lieu_de_deces": "Marseille",
        "photo": "rimbaud.png",
        "oeuvres_majeures": "Le Bateau ivre - Une saison en enfer - Illuminations",
        "citation1": "\"L'amour est à réinventer.\"",
        "oeuvreCitation1": "Une saison en enfer",
        "citation2": "\"On n'est pas sérieux, quand on a dix-sept ans.\"",
        "oeuvreCitation2": "Poésies",
        "citation3": "\"Je est un autre.\"",
        "oeuvreCitation3": "Lettre à Paul Demeny"
    },
    {
        "id": 1760,
        "nom": "Romains",
        "prenom": "Jûles",
        "date_de_naissance": "26 août 1885",
        "lieu_de_naissance": "Saint-Julien-Chapteuil",
        "date_de_deces": "14 août 1972",
        "lieu_de_deces": "Paris",
        "photo": "romains.jpg",
        "oeuvres_majeures": "Les hommes de bonne volonté - Knock ou le Triomphe de la médecine",
        "citation1": "\"Les gens bien portants sont des malades qui s’ignorent.\"",
        "oeuvreCitation1": "Knock",
        "citation2": "\"Le temps passe. Et chaque fois qu'il y a du temps qui passe, il y a quelque chose qui s'efface.\"",
        "oeuvreCitation2": "Les hommes de bonne volonté",
        "citation3": "\"On récompense des écrivains parfois pour leur oeuvre. Pourquoi n'en punit-on jamais ?\"",
        "oeuvreCitation3": "Amitiés et rencontres"
    },
    {
        "id": 1770,
        "nom": "Ronsard",
        "prenom": "Pierre de",
        "date_de_naissance": " ? septembre 1524",
        "lieu_de_naissance": "Couture-sur-Loir",
        "date_de_deces": "27 décembre 1585",
        "lieu_de_deces": "Saint-Cosme",
        "photo": "ronsard.jpg",
        "oeuvres_majeures": "Les Odes - Les Amours - Les Hymnes - Les Discours - Les Sonnets pour Hélène",
        "citation1": "\"Celui qui se connaît est seul maître de soi.”\"",
        "oeuvreCitation1": "Institution pour l’adolescence du roi très chrétien",
        "citation2": "\"Vivez si m’en croyez, n’attendez à demain. Cueillez dès aujourd’hui les roses de la vie.\"",
        "oeuvreCitation2": "Sonnets pour Hélène",
        "citation3": "\"Mais toujours le plaisir de douleur s'accompagne.\"",
        "oeuvreCitation3": "Sonnets"
    },
    {
        "id": 1775,
        "nom": "Rostand",
        "prenom": "Edmond",
        "date_de_naissance": "1er avril 1868",
        "lieu_de_naissance": "Marseille",
        "date_de_deces": "2 décembre 1918",
        "lieu_de_deces": "Paris",
        "photo": "rostand.jpg",
        "oeuvres_majeures": "Cyrano de Bergerac - L'Aiglon - Chantecler",
        "citation1": "\"Des larmes au baiser il n'y a qu'un frisson !”\"",
        "oeuvreCitation1": "Cyrano de Bergerac, III, 10 (1897)",
        "citation2": "\"La meilleure prière est la plus clandestine.\"",
        "oeuvreCitation2": "La Samaritaine (1897)",
        "citation3": "\"Les haines de races ne sont jamais au fond, que des haines de places.\"",
        "oeuvreCitation3": "Chantecler, I, 1 (1904)"
    },
    {
        "id": 1780,
        "nom": "Rousseau",
        "prenom": "Jean-Jacques",
        "date_de_naissance": "28 juin 1712",
        "lieu_de_naissance": "Genève",
        "date_de_deces": "2 juillet 1778",
        "lieu_de_deces": "Ermenonville",
        "photo": "rousseau.jpg",
        "oeuvres_majeures": "Du Contrat social - L'Encyclopédie (avec Diderot et d'Alembert)",
        "citation1": "\"L'argent qu'on possède est l'instrument de la liberté, celui qu'on pourchasse est celui de la servitude.\"",
        "oeuvreCitation1": "Les Confessions",
        "citation2": "\"Qui rougit est déjà coupable, la vraie innocence n'a honte de rien.\"",
        "oeuvreCitation2": "Emile, ou de l'Education",
        "citation3": "\"Les lois sont toujours utiles à ceux qui possèedent et nuisibles à ceux qui n'ont rien.\"",
        "oeuvreCitation3": "Du Contrat social"
    },
    {
        "id": 1800,
        "nom": "Saint-Exupéry",
        "prenom": "Antoine de",
        "date_de_naissance": "29 juin 1900",
        "lieu_de_naissance": "Lyon",
        "date_de_deces": "31 juillet 1944",
        "lieu_de_deces": "Marseille",
        "photo": "saint_exupery.jpg",
        "oeuvres_majeures": "Vol de nuit - Le Petit Prince - Terre des hommes",
        "citation1": "\"Aimer, ce n’est pas se regarder l’un l’autre, c’est regarder ensemble dans la même direction.\"",
        "oeuvreCitation1": "Terre des hommes",
        "citation2": "\"On ne voit bien qu’avec le coeur. L’essentiel est invisible pour les yeux.\"",
        "oeuvreCitation2": "Le Petit Prince",
        "citation3": "\"Toutes les grandes personnes ont d’abord été des enfants, mais peu d’entre elles s’en souviennent.\"",
        "oeuvreCitation3": "Le petit Prince"
    },
    {
        "id": 1830,
        "nom": "Shakespeare",
        "prenom": "William",
        "date_de_naissance": "26 avril 1564",
        "lieu_de_naissance": "Stratford-upon-Avon",
        "date_de_deces": "23 avril 1616",
        "lieu_de_deces": "Stratford-upon-Avon",
        "photo": "shakespeare.jpg",
        "oeuvres_majeures": "Roméo et Juliette - Hamlet, prince de Danemark - Macbeth - Othello ou le maure de Venise - Le Roi Lear",
        "citation1": "\"Etre ou ne pas être : telle est la question.\"",
        "oeuvreCitation1": "Hamlet, acte 3, scène 1 (1601)",
        "citation2": "\"L'amour ne voit pas avec les yeux, mais avec l'âme.\"",
        "oeuvreCitation2": "Songe d'une nuit d'été (1595)",
        "citation3": "\"Ce qu'on a fait est fait et ne peut se défaire !\"",
        "oeuvreCitation3": "Macbeth (1605)"
    },
    {
        "id": 1860,
        "nom": "Stendhal",
        "prenom": "(Henri Beyle)",
        "date_de_naissance": "23 janvier 1783",
        "lieu_de_naissance": "Grenoble",
        "date_de_deces": "23 mars 1842",
        "lieu_de_deces": "Paris",
        "photo": "stendhal.jpg",
        "oeuvres_majeures": "Le Rouge et le Noir - Lucien Leuwen - La Chartreuse de Parme",
        "citation1": "\"La beauté n'est que la promesse du bonheur.\"",
        "oeuvreCitation1": "De l'amour (1822)",
        "citation2": "\"On est ce qu'on peut, mais on sent ce qu'on est.\"",
        "oeuvreCitation2": "",
        "citation3": "\"J'ai assez vécu pour voir que différence engendre haine.\"",
        "oeuvreCitation3": "Le Rouge et le Noir"
    },
    {
        "id": 1900,
        "nom": "Tolstoï",
        "prenom": "Léon",
        "date_de_naissance": "28 août 1828",
        "lieu_de_naissance": "Iasnaïa Poliana",
        "date_de_deces": "7 novembre 1910",
        "lieu_de_deces": "Astapovo",
        "photo": "tolstoi.jpg",
        "oeuvres_majeures": "Guerre et Paix - Anna Karénine - La Mort d'Ivan Illitch - Résurrection",
        "citation1": "\"Il n'y a pas d'autre amour que celui qui consiste à donner sa vie pour ceux qu'on aime.\"",
        "oeuvreCitation1": "Dela vie (1889)",
        "citation2": "\"En matière de sentiment, le manque de logique est la meilleure preuve de la sincérité.\"",
        "oeuvreCitation2": "Songe d'une nuit d'été (1595)",
        "citation3": "\"Tous les hommes font la même erreur, de s'imaginer que bonheur veut dire que tous les voeux se réalisent.\"",
        "oeuvreCitation3": ""
    },
    {
        "id": 1990,
        "nom": "Twain",
        "prenom": "Mark",
        "date_de_naissance": "30 novembre 1835",
        "lieu_de_naissance": "Florida",
        "date_de_deces": "21 avril 1910",
        "lieu_de_deces": "Redding",
        "photo": "twain.jpg",
        "oeuvres_majeures": "Les Aventures de Tom Sawyer - Les Aventures de Huckleberry Finn",
        "citation1": "\"Ils ne savaient pas que c'était impossible, alors ils l'ont fait.\"",
        "oeuvreCitation1": "Les pensées et aphorismes (1835-1910)",
        "citation2": "\"Dans le doute, dîtes la vérité.\"",
        "oeuvreCitation2": "La tragédie de Pudd'nhead Wilson (1894)",
        "citation3": "\"La gentillesse est le langage qu'un sourd peut entendre et qu'un aveugle peut voir\"",
        "oeuvreCitation3": "Les pensées et aphorismes (1835-1910)"
    },
    {
        "id": 2100,
        "nom": "Valéry",
        "prenom": "Paul",
        "date_de_naissance": "30 octobre 1871",
        "lieu_de_naissance": "Sète",
        "date_de_deces": "20 juillet 1945",
        "lieu_de_deces": "Paris",
        "photo": "paul_valery.jpg",
        "oeuvres_majeures": "Introduction à la méthode de Léonard de Vinci - La Soirée avec Monsieur Teste - La Jeune Parque - Charmes - Degas Danse Dessin",
        "citation1": "\"Le diplôme est l'ennemi mortel de la culture.\"",
        "oeuvreCitation1": "",
        "citation2": "\"Un chef est un homme qui a besoin des autres.\"",
        "oeuvreCitation2": "Mauvaises pensées et autres",
        "citation3": "\"Les hommes se distinguent par ce qu'ils montrent et se ressemblent par ce qu'ils cachent.\"",
        "oeuvreCitation3": "Mélange"
    },
    {
        "id": 2125,
        "nom": "Verlaine",
        "prenom": "Paul",
        "date_de_naissance": "30 mars 1844",
        "lieu_de_naissance": "Metz",
        "date_de_deces": "8 janvier 1896",
        "lieu_de_deces": "Paris",
        "photo": "verlaine.jpeg",
        "oeuvres_majeures": "Poèmes saturniens - Fêtes galantes - Romances sans paroles - Sagesse - Les Poèmes maudits",
        "citation1": "\"Les sanglots longs des violons de l'automne blessent mon cœur d'une langueur monotone. Tout suffocant et blême, quand sonne l'heure, je me souviens des jours anciens et je pleure ; et je m'en vais au vent mauvais qui m'emporte deçà, delà, pareil à la feuille morte.\"",
        "oeuvreCitation1": "Poèmes saturniens, Chanson d'automne (1866)",
        "citation2": "\"Baiser ! Rose trémière au jardin des caresses !\"",
        "oeuvreCitation2": "Il bacio, Poèmes saturniens (1866)",
        "citation3": "\"Je suis riche de tes beaux yeux.\"",
        "oeuvreCitation3": "Je suis plus pauvre que jamais (1891)"
    },
    {
        "id": 2130,
        "nom": "Verne",
        "prenom": "Jûles",
        "date_de_naissance": "8 février 1828",
        "lieu_de_naissance": "Nantes",
        "date_de_deces": "24 mars 1905",
        "lieu_de_deces": "Amiens",
        "photo": "verne.jpg",
        "oeuvres_majeures": "Vingt Mille Lieues sous les mers - Voyage au centre de la Terre - De la Terre à la Lune - Le Tour du monde en quatre-vingt jours - L'Ile mystérieuse - Cinq Semaines en ballon",
        "citation1": "\"C'est à force de répandre le bon grain qu'une semence finit par tomber dans un sillon fertile.\"",
        "oeuvreCitation1": "Les Naufragés du 'Jonathan'",
        "citation2": "\"C'était un honorable praticien qui guérissait les malades de toutes les maladies, excepté de celle dont ils mouraient.\"",
        "oeuvreCitation2": "Le docteur Ox",
        "citation3": "\"Les passeports ne servent jamais qu'à gêner les honnêtes gens et à favoriser la fuite des coquins.\"",
        "oeuvreCitation3": "Le Tour du monde en quatre-vingt jours"
    },
    {
        "id": 2150,
        "nom": "Voltaire",
        "prenom": "(François-Marie Arouet)",
        "date_de_naissance": "21 novembre 1694",
        "lieu_de_naissance": "Paris",
        "date_de_deces": "30 mai 1778",
        "lieu_de_deces": "Paris",
        "photo": "voltaire.png",
        "oeuvres_majeures": "Lettres philosophiques - Zadig ou la Destinée - Candide ou l'Optimisme - Dictionnaire philosophique - L'Ingénu",
        "citation1": "\"On parle toujours mal quand on n'a rien à dire.\"",
        "oeuvreCitation1": "",
        "citation2": "\"Le fanatisme est un monstre qui ose se dire le fils de la religion.\"",
        "oeuvreCitation2": "",
        "citation3": "\"Le malheur des uns fait le bonheur des autres.\"",
        "oeuvreCitation3": ""
    },
    {
        "id": 2400,
        "nom": "Yourcenar",
        "prenom": "Marguerite",
        "date_de_naissance": "8 juin 1903",
        "lieu_de_naissance": "Bruxelles",
        "date_de_deces": "17 décembre 1987",
        "lieu_de_deces": "Bar Harbor (Etats-Unis)",
        "photo": "yourcenar.jpg",
        "oeuvres_majeures": "Mémoires d'Hadrien - L'Oeuvre au noir - Nouvelles orientales - Alexis ou le Traité du vain combat - Mishima ou la Vision du vide",
        "citation1": "\"Le silence est fait de paroles que l'on n'a pas dites.\"",
        "oeuvreCitation1": "",
        "citation2": "\"Personne ne sait encore si tout ne vit que pour mourir ou ne meurt que pour renaître.\"",
        "oeuvreCitation2": "Anna, soror...",
        "citation3": "\"Tout moment est dernier, parce qu'il est unique.\"",
        "oeuvreCitation3": ""
    },
    {
        "id": 2500,
        "nom": "Zola",
        "prenom": "Emile",
        "date_de_naissance": "2 avril 1840",
        "lieu_de_naissance": "Paris",
        "date_de_deces": "29 septembre 1902",
        "lieu_de_deces": "Paris",
        "photo": "zola.jpg",
        "oeuvres_majeures": "Thérèse Raquin - Les Rougon-Macquart dont L'Assommoir, Nana, Germinal - Le Roman expérimental",
        "citation1": "\"La vérité est en marche et rien ne l’arrêtera.\"",
        "oeuvreCitation1": "L’Affaire Dreyfus. La Vérité en marche",
        "citation2": "\"On ne saurait aller trop loin dans la connaissance de l'homme.\"",
        "oeuvreCitation2": "Livres d'aujourd'hui et de demain",
        "citation3": "\"Aucun bonheur n'est possible dans l'ignorance, la certitude seule fait la vie calme.\"",
        "oeuvreCitation3": ""
    }
]